callmonitor/__init__.py
callmonitor/args.py
callmonitor/counter.py
callmonitor/db.py
callmonitor/handler.py
callmonitor/monitor.py
callmonitor/registry.py
callmonitor/settings.py
callmonitor/singleton.py
callmonitor/version.py
callmonitor-0.3.7.dist-info/LICENSE
callmonitor-0.3.7.dist-info/METADATA
callmonitor-0.3.7.dist-info/WHEEL
callmonitor-0.3.7.dist-info/top_level.txt
callmonitor-0.3.7.dist-info/RECORD
