Metadata-Version: 2.1
Name: callmonitor
Version: 0.3.7
Summary: A light-weight package that allows you to monitor function calls with ease.
Home-page: https://github.com/JBlaschke/call-monitor
Author: Johannes Blaschke
Author-email: johannes@blaschke.science
License: UNKNOWN
Platform: UNKNOWN
Classifier: Programming Language :: Python :: 3
Classifier: License :: OSI Approved :: MIT License
Classifier: Operating System :: OS Independent
Requires-Python: >=3.6
Requires-Dist: numpy
